Metadata-Version: 2.1
Name: wotApiPy
Version: 0.1
Summary: World of Tanks Api for Python
Author-email: georgiy.shalaev2009@gmail.com
